tm_config_server_client_python/Playclient.py
tm_config_server_client_python/Pythonclient.py
tm_config_server_client_python/__init__.py
tm_config_server_client_python-1.0.dist-info/METADATA
tm_config_server_client_python-1.0.dist-info/WHEEL
tm_config_server_client_python-1.0.dist-info/top_level.txt
tm_config_server_client_python-1.0.dist-info/RECORD
