Metadata-Version: 2.1
Name: tm-config-server-client-python
Version: 1.0
Summary: Gaussian and Binomial distributions
Home-page: UNKNOWN
Author: UNKNOWN
Author-email: jayantreddybodkurwar@gmail.com
License: UNKNOWN
Platform: UNKNOWN
